cites_model/__init__.py
cites_model/cites_additional.py
cites_model/cites_common.py
cites_model/cites_document.py
cites_model/cites_reg_card.py
cites_model/cites_statement.py
cites_model/cites_swin.py
cites_model/cites_taxon.py
cites_model/cites_template.py
cites_model/customs_permit.py
cites_model-1.7.21.dist-info/licenses/LICENSE
cites_model-1.7.21.dist-info/METADATA
cites_model-1.7.21.dist-info/WHEEL
cites_model-1.7.21.dist-info/top_level.txt
cites_model-1.7.21.dist-info/RECORD
