Metadata-Version: 2.4
Name: cites-model
Version: 1.7.21
Summary: CITES Data Model
Author-email: Data Developer <info@sysnet.cz>
Project-URL: Homepage, https://github.com/SYSNET-CZ/models/tree/main/cites
Classifier: Development Status :: 5 - Production/Stable
Classifier: Programming Language :: Python :: 3
Classifier: Intended Audience :: Developers
Classifier: License :: Free For Home Use
Classifier: Natural Language :: Czech
Classifier: Operating System :: OS Independent
Classifier: Topic :: Software Development :: Libraries
Requires-Python: >=3.10
License-File: LICENSE
Requires-Dist: typing-extensions>=4
Requires-Dist: sysnet-pyutils>=1.4.9
Requires-Dist: pydantic[email]>=2.11.3
Dynamic: license-file
